trialbot/__init__.py
trialbot/data/__init__.py
trialbot/data/_translation_base.py
trialbot/data/dataset.py
trialbot/data/field.py
trialbot/data/iterator.py
trialbot/data/ns_vocabulary.py
trialbot/data/translator.py
trialbot/data/datasets/__init__.py
trialbot/data/datasets/consecutive_lines_dataset.py
trialbot/data/datasets/file_dataset.py
trialbot/data/datasets/index_dataset.py
trialbot/data/datasets/json_dataset.py
trialbot/data/datasets/jsonl_dataset.py
trialbot/data/datasets/pickle_dataset.py
trialbot/data/datasets/redis_dataset.py
trialbot/data/datasets/seq2dict_dataset.py
trialbot/data/datasets/tabular_dataset.py
trialbot/data/datasets/tsv_dataset.py
trialbot/data/fields/__init__.py
trialbot/data/fields/seq_field.py
trialbot/data/iterators/__init__.py
trialbot/data/iterators/bucket_iterator.py
trialbot/data/iterators/cluster_iterator.py
trialbot/data/iterators/random_iterator.py
trialbot/data/translators/__init__.py
trialbot/data/translators/known_field_translator.py
trialbot/training/__init__.py
trialbot/training/event_engine.py
trialbot/training/extensions.py
trialbot/training/hparamset.py
trialbot/training/opt_parser.py
trialbot/training/select_optims.py
trialbot/training/trial_bot.py
trialbot/training/trial_registry.py
trialbot/training/updater.py
trialbot/training/updaters/__init__.py
trialbot/training/updaters/testing_updater.py
trialbot/training/updaters/training_updater.py
trialbot/utils/__init__.py
trialbot/utils/file_reader.py
trialbot/utils/fix_seed.py
trialbot/utils/grid_search_helper.py
trialbot/utils/move_to_device.py
trialbot/utils/prepend_pythonpath.py
trialbot/utils/root_finder.py
trialbot-0.5.1.dist-info/LICENSE
trialbot-0.5.1.dist-info/METADATA
trialbot-0.5.1.dist-info/WHEEL
trialbot-0.5.1.dist-info/top_level.txt
trialbot-0.5.1.dist-info/RECORD
