Metadata-Version: 2.1
Name: trialbot
Version: 0.5.1
Summary: A lightweight training framework for PyTorch
Home-page: https://github.com/zxteloiv/trialbot
Author: zxteloiv
Author-email: zxteloiv@gmail.com
Classifier: Programming Language :: Python :: 3
Classifier: License :: OSI Approved :: MIT License
Classifier: Operating System :: OS Independent
License-File: LICENSE
